flake8_walrus.py
flake8_walrus-1.2.0.dist-info/LICENSE
flake8_walrus-1.2.0.dist-info/METADATA
flake8_walrus-1.2.0.dist-info/WHEEL
flake8_walrus-1.2.0.dist-info/entry_points.txt
flake8_walrus-1.2.0.dist-info/top_level.txt
flake8_walrus-1.2.0.dist-info/RECORD
